pytest_store/__init__.py
pytest_store/plugin.py
pytest_store/store.py
pytest_store/stores/__init__.py
pytest_store/stores/_store_base.py
pytest_store/stores/list_dict.py
pytest_store/stores/pandas_df.py
pytest_store/stores/polars_df.py
pytest_store/types.py
pytest_store-0.0.6.dist-info/LICENSE
pytest_store-0.0.6.dist-info/METADATA
pytest_store-0.0.6.dist-info/WHEEL
pytest_store-0.0.6.dist-info/entry_points.txt
pytest_store-0.0.6.dist-info/RECORD
