Metadata-Version: 2.3
Name: pytest-store
Version: 0.0.6
Summary: Pytest plugin to store values from test runs
License: MIT
Author: tb
Author-email: tb@wodore.com
Requires-Python: >=3.10,<3.14
Classifier: Development Status :: 3 - Alpha
Classifier: Intended Audience :: Developers
Classifier: License :: OSI Approved :: MIT License
Classifier: Operating System :: MacOS :: MacOS X
Classifier: Operating System :: Microsoft :: Windows
Classifier: Operating System :: POSIX
Classifier: Programming Language :: Python :: 3
Classifier: Programming Language :: Python :: 3.10
Classifier: Programming Language :: Python :: 3.11
Classifier: Programming Language :: Python :: 3.12
Classifier: Programming Language :: Python :: 3.13
Classifier: Topic :: Software Development :: Libraries
Classifier: Topic :: Software Development :: Testing
Classifier: Topic :: Utilities
Provides-Extra: all
Provides-Extra: database
Provides-Extra: excel
Provides-Extra: pandas
Provides-Extra: parquet
Provides-Extra: polars
Requires-Dist: fastparquet (>=2024.11,<2025.0) ; extra == "all" or extra == "parquet"
Requires-Dist: msgspec (>=0.19,<0.20)
Requires-Dist: openpyxl (>=3.1,<4.0) ; extra == "all" or extra == "excel"
Requires-Dist: pandas (>=2.3,<3.0) ; extra == "all" or extra == "pandas"
Requires-Dist: polars (>=1.31,<2.0) ; extra == "all" or extra == "polars"
Requires-Dist: pyarrow (>=21.0,<22.0) ; extra == "all" or extra == "parquet"
Requires-Dist: pytest (>=7.0.0)
Requires-Dist: pyyaml (>=6.0,<7.0)
Requires-Dist: sqlalchemy (>=2.0,<3.0) ; extra == "all" or extra == "database"
Requires-Dist: tabulate (>=0.9.0,<0.10.0)
Requires-Dist: xlsx2csv (>=0.8,<0.9) ; extra == "all" or extra == "excel"
Requires-Dist: xlsxwriter (>=3.2,<4.0) ; extra == "all" or extra == "excel"
Project-URL: Changelog, https://github.com/TBxy/pytest-store/blob/main/CHANGELOG.md
Project-URL: Issues, https://github.com/TBxy/pytest-store/issues
Project-URL: Repository, https://github.com/TBxy/pytest-store
